MANIFEST.in
README
README.md
plugin_loader.py
setup.py
plugin_loader.egg-info/PKG-INFO
plugin_loader.egg-info/SOURCES.txt
plugin_loader.egg-info/dependency_links.txt
plugin_loader.egg-info/not-zip-safe
plugin_loader.egg-info/top_level.txt